{"inkVersion":20,"root":[[{"->":"H_B00"},["done",{"#f":5,"#n":"g-0"}],null],"done",{"H_B00":[["ev",0,3,"rnd","/ev",["du","ev",0,"==","/ev",{"->":".^.b","c":true},{"b":["pop","\n","^O co chodzi?","\n",{"->":".^.^.^.10"},null]}],["du","ev",1,"==","/ev",{"->":".^.b","c":true},{"b":["pop","\n","^Słucham.","\n",{"->":".^.^.^.10"},null]}],["du","ev",2,"==","/ev",{"->":".^.b","c":true},{"b":["pop","\n","^W czym problem?","\n",{"->":".^.^.^.10"},null]}],["du","ev",3,"==","/ev",{"->":".^.b","c":true},{"b":["pop","\n","^W czym mogę pomóc?","\n",{"->":".^.^.^.10"},null]}],"pop","nop","\n","ev","str","^def","/str","/ev",{"temp=":"odp"},"ev",0,3,"rnd","/ev",["du","ev",0,"==","/ev",{"->":".^.b","c":true},{"b":["pop","\n","ev","str","^Nic, nic","/str","/ev",{"temp=":"odp","re":true},{"->":".^.^.^.28"},null]}],["du","ev",1,"==","/ev",{"->":".^.b","c":true},{"b":["pop","\n","ev","str","^Już nie ważne","/str","/ev",{"temp=":"odp","re":true},{"->":".^.^.^.28"},null]}],["du","ev",2,"==","/ev",{"->":".^.b","c":true},{"b":["pop","\n","ev","str","^Tak tylko sprawdzam czy jeszcze działasz","/str","/ev",{"temp=":"odp","re":true},{"->":".^.^.^.28"},null]}],["du","ev",3,"==","/ev",{"->":".^.b","c":true},{"b":["pop","\n","ev","str","^Właśnie sobie przypomniałem","/str","/ev",{"temp=":"odp","re":true},{"->":".^.^.^.28"},null]}],"pop","nop","\n","ev","str","^Co to za miejsce?","/str","/ev",{"*":".^.c-0","flg":4},"ev","str","^Co mam tu zrobić?","/str","/ev",{"*":".^.c-1","flg":4},"ev","str","ev",{"VAR?":"odp"},"out","/ev","/str","/ev",{"*":".^.c-2","flg":4},{"c-0":["\n",{"->":"H_B01"},{"#f":5}],"c-1":["\n",{"->":"H_B02"},{"#f":5}],"c-2":["\n","end",{"#f":5}]}],{"#f":1}],"H_B01":["^Jesteś w centrum, gdzie schodzą się i przenikają wszystkie wymiary.","\n","^Procesy te generują olbrzymie ilości energii, która promieniuje zieloną poświatą.","\n","end",{"#f":1}],"H_B02":["^Podłącz przewód do wybranego źródła, aby przekierować energię do katalizatora.<n>Dzięki temu nastąpi chwilowe scalenie tego miejsca z wybranym wymiarem, umożliwiając ingerencję w jego strukturę.","\n","^Scalenie i ingerencja w inne wymiary jest niezbędna do naprawy wyrządzonych zniszczeń.<n>Aktualne możliwości maszyny nie pozwalają na przeprowadzenie takich manipulacji.","\n","end",{"#f":1}],"#f":1}],"listDefs":{}}